pygetcsv/__init__.py
pygetcsv/pygetcsv.py
pygetcsv-0.0.1.dist-info/METADATA
pygetcsv-0.0.1.dist-info/WHEEL
pygetcsv-0.0.1.dist-info/top_level.txt
pygetcsv-0.0.1.dist-info/RECORD
